gift_core/__init__.py
gift_core/_version.py
gift_core/constants.py
gift_core/dashboard.py
gift_core/experimental.py
gift_core/monte_carlo.py
gift_core/relations.py
gift_core/scales.py
gift_core/topology.py
gift_core/torch_optim.py
gift_core/analysis/__init__.py
gift_core/analysis/intervals.py
gift_core/analysis/joyce_certificate.py
gift_core/g2/__init__.py
gift_core/g2/constraints.py
gift_core/g2/g2_form.py
gift_core/g2/holonomy.py
gift_core/g2/torsion.py
gift_core/geometry/__init__.py
gift_core/geometry/acyl_cy3.py
gift_core/geometry/k3_surface.py
gift_core/geometry/k7_metric.py
gift_core/geometry/tcs_construction.py
gift_core/harmonic/__init__.py
gift_core/harmonic/betti_validation.py
gift_core/harmonic/harmonic_forms.py
gift_core/harmonic/hodge_laplacian.py
gift_core/mckay/__init__.py
gift_core/monster/__init__.py
gift_core/nn/__init__.py
gift_core/nn/fourier_features.py
gift_core/nn/g2_pinn.py
gift_core/nn/loss_functions.py
gift_core/nn/training.py
gift_core/physics/__init__.py
gift_core/physics/coupling_constants.py
gift_core/physics/mass_spectrum.py
gift_core/physics/yukawa_tensor.py
gift_core/pipeline/__init__.py
gift_core/pipeline/config.py
gift_core/pipeline/full_pipeline.py
gift_core/primes/__init__.py
gift_core/sequences/__init__.py
gift_core/verification/__init__.py
gift_core/verification/certificate.py
gift_core/verification/lean_export.py
gift_core/verification/numerical_bounds.py
giftpy-5.0.0.dist-info/licenses/LICENSE
giftpy-5.0.0.dist-info/METADATA
giftpy-5.0.0.dist-info/WHEEL
giftpy-5.0.0.dist-info/top_level.txt
giftpy-5.0.0.dist-info/RECORD
