Metadata-Version: 2.4
Name: giftpy
Version: 5.0.0
Summary: GIFT mathematical core - Formally verified constants (Lean 4 + Coq)
Author-email: Brieuc de La Fourniere <brieuc@bdelaf.com>
License: MIT
Project-URL: Homepage, https://github.com/gift-framework/core
Project-URL: Documentation, https://github.com/gift-framework/GIFT
Project-URL: Repository, https://github.com/gift-framework/core
Project-URL: Lean Proofs, https://github.com/gift-framework/core/tree/main/Lean
Project-URL: Coq Proofs, https://github.com/gift-framework/core/tree/main/COQ
Keywords: physics,mathematics,formal-verification,lean4,coq,standard-model,E8,topology
Classifier: Development Status :: 5 - Production/Stable
Classifier: Intended Audience :: Science/Research
Classifier: License :: OSI Approved :: MIT License
Classifier: Programming Language :: Python :: 3
Classifier: Programming Language :: Python :: 3.9
Classifier: Programming Language :: Python :: 3.10
Classifier: Programming Language :: Python :: 3.11
Classifier: Programming Language :: Python :: 3.12
Classifier: Topic :: Scientific/Engineering :: Physics
Classifier: Topic :: Scientific/Engineering :: Mathematics
Requires-Python: >=3.9
License-File: LICENSE
Provides-Extra: dev
Requires-Dist: pytest>=7.0; extra == "dev"
Requires-Dist: pytest-cov; extra == "dev"
Requires-Dist: black; extra == "dev"
Requires-Dist: ruff; extra == "dev"
Dynamic: license-file
